rejected/__init__.py
rejected/consumer.py
rejected/controller.py
rejected/data.py
rejected/log.py
rejected/mcp.py
rejected/mixins.py
rejected/process.py
rejected/state.py
rejected/statsd.py
rejected/testing.py
rejected/utils.py
rejected-3.23.1.dist-info/LICENSE
rejected-3.23.1.dist-info/METADATA
rejected-3.23.1.dist-info/WHEEL
rejected-3.23.1.dist-info/entry_points.txt
rejected-3.23.1.dist-info/top_level.txt
rejected-3.23.1.dist-info/zip-safe
rejected-3.23.1.dist-info/RECORD
