Metadata-Version: 2.1
Name: rejected
Version: 3.23.1
Summary: Rejected is a Python RabbitMQ Consumer Framework and Controller Daemon
Home-page: https://github.com/gmr/rejected
Author: Gavin M. Roy
Author-email: gavinmroy@gmail.com
License: BSD
Keywords: amqp rabbitmq
Classifier: Development Status :: 5 - Production/Stable
Classifier: Intended Audience :: Developers
Classifier: Programming Language :: Python :: 2
Classifier: Programming Language :: Python :: 2.7
Classifier: Programming Language :: Python :: 3
Classifier: Programming Language :: Python :: 3.5
Classifier: Programming Language :: Python :: 3.6
Classifier: Programming Language :: Python :: 3.7
Classifier: Programming Language :: Python :: 3.8
Classifier: Programming Language :: Python :: 3.9
Classifier: Programming Language :: Python :: Implementation :: CPython
Classifier: Programming Language :: Python :: Implementation :: PyPy
Classifier: License :: OSI Approved :: BSD License
License-File: LICENSE
Requires-Dist: helper <3,>=2.5.0
Requires-Dist: pika <3,>=1.2.0
Requires-Dist: psutil
Requires-Dist: pyyaml <7,>=5.3.1
Requires-Dist: tornado
Provides-Extra: html
Requires-Dist: beautifulsoup4 ; extra == 'html'
Provides-Extra: influxdb
Requires-Dist: sprockets-influxdb ; extra == 'influxdb'
Provides-Extra: msgpack
Requires-Dist: u-msgpack-python ; extra == 'msgpack'
Provides-Extra: sentry
Requires-Dist: raven ; extra == 'sentry'
Provides-Extra: testing
Requires-Dist: beautifulsoup4 ; extra == 'testing'
Requires-Dist: u-msgpack-python ; extra == 'testing'
Requires-Dist: sphinx ; extra == 'testing'
Requires-Dist: raven ; extra == 'testing'
Requires-Dist: sprockets-influxdb ; extra == 'testing'
